{
  "return_1d": [
    {
      "date": "2026-01-21",
      "value": -0.0008075999999999476
    },
    {
      "date": "2026-01-21",
      "value": -0.0008075999999999476
    },
    {
      "date": "2026-01-21",
      "value": -0.0008075999999999476
    },
    {
      "date": "2026-01-21",
      "value": -0.0008075999999999476
    },
    {
      "date": "2026-01-21",
      "value": -0.0008075999999999476
    },
    {
      "date": "2026-01-21",
      "value": -0.001213899999999994
    },
    {
      "date": "2026-01-22",
      "value": 0.004979100000000035
    },
    {
      "date": "2026-01-22",
      "value": 0.0025405999999999766
    }
  ],
  "alpha_1d": [
    {
      "date": "2026-01-21",
      "value": 0.01932022324532246
    },
    {
      "date": "2026-01-21",
      "value": 0.01932022324532246
    },
    {
      "date": "2026-01-21",
      "value": 0.01932022324532246
    },
    {
      "date": "2026-01-21",
      "value": 0.01932022324532246
    },
    {
      "date": "2026-01-21",
      "value": 0.01932022324532246
    },
    {
      "date": "2026-01-21",
      "value": 0.018913923245322414
    },
    {
      "date": "2026-01-22",
      "value": -0.009925129259510668
    },
    {
      "date": "2026-01-22",
      "value": -0.008792516902281498
    }
  ],
  "volatility": [
    {
      "date": "2026-01-21",
      "value": 0.0
    },
    {
      "date": "2026-01-21",
      "value": 0.0
    },
    {
      "date": "2026-01-21",
      "value": 0.0
    },
    {
      "date": "2026-01-21",
      "value": 0.0
    },
    {
      "date": "2026-01-21",
      "value": 0.0
    },
    {
      "date": "2026-01-21",
      "value": 0.0
    },
    {
      "date": "2026-01-22",
      "value": 0.0
    },
    {
      "date": "2026-01-22",
      "value": 0.0
    }
  ],
  "sharpe_ratio": [
    {
      "date": "2026-01-21",
      "value": 0.0
    },
    {
      "date": "2026-01-21",
      "value": 0.0
    },
    {
      "date": "2026-01-21",
      "value": 0.0
    },
    {
      "date": "2026-01-21",
      "value": 0.0
    },
    {
      "date": "2026-01-21",
      "value": 0.0
    },
    {
      "date": "2026-01-21",
      "value": 0.0
    },
    {
      "date": "2026-01-22",
      "value": 0.0
    },
    {
      "date": "2026-01-22",
      "value": 0.0
    }
  ],
  "drawdown": [
    {
      "date": "2026-01-21",
      "value": 0.0
    },
    {
      "date": "2026-01-21",
      "value": 0.0
    },
    {
      "date": "2026-01-21",
      "value": 0.0
    },
    {
      "date": "2026-01-21",
      "value": 0.0
    },
    {
      "date": "2026-01-21",
      "value": 0.0
    },
    {
      "date": "2026-01-21",
      "value": -0.0008113000000000466
    },
    {
      "date": "2026-01-22",
      "value": -0.0008113000000000466
    },
    {
      "date": "2026-01-22",
      "value": -0.0008113000000000466
    }
  ],
  "rolling_metrics": {
    "avg_daily_return": 0.0002834750000000349,
    "avg_alpha": 0.01209967416376782,
    "avg_sharpe": 0.0,
    "trend_return": "improving",
    "trend_sharpe": "stable"
  }
}